kuda/__author__.py
kuda/__init__.py
kuda/__version__.py
kuda/api.py
kuda/error.py
kuda/savings.py
kuda_python-1.0.2.dist-info/LICENSE
kuda_python-1.0.2.dist-info/METADATA
kuda_python-1.0.2.dist-info/WHEEL
kuda_python-1.0.2.dist-info/top_level.txt
kuda_python-1.0.2.dist-info/RECORD
