Metadata-Version: 2.1
Name: kuda-python
Version: 1.0.2
Summary: Kuda OpenAPI Python Library
Home-page: https://kuda-python.readthedocs.io/
Author: Chiemezie Njoku
Author-email: njokuchiemezie01@gmail.com
License: MIT
Platform: UNKNOWN
Classifier: Intended Audience :: Developers
Classifier: License :: OSI Approved :: MIT License
Classifier: Programming Language :: Python
Classifier: Programming Language :: Python :: 3
Classifier: Programming Language :: Python :: 3.6
Classifier: Programming Language :: Python :: 3.7
Classifier: Programming Language :: Python :: 3.8
Classifier: Programming Language :: Python :: 3.9
Classifier: Operating System :: OS Independent
License-File: LICENSE
Requires-Dist: requests
